README.md
setup.py
pyu2f/__init__.py
pyu2f/apdu.py
pyu2f/errors.py
pyu2f/hardware.py
pyu2f/hidtransport.py
pyu2f/model.py
pyu2f/u2f.py
pyu2f.egg-info/PKG-INFO
pyu2f.egg-info/SOURCES.txt
pyu2f.egg-info/dependency_links.txt
pyu2f.egg-info/requires.txt
pyu2f.egg-info/top_level.txt
pyu2f.egg-info/zip-safe
pyu2f/convenience/__init__.py
pyu2f/convenience/authenticator.py
pyu2f/convenience/baseauthenticator.py
pyu2f/convenience/customauthenticator.py
pyu2f/convenience/localauthenticator.py
pyu2f/hid/__init__.py
pyu2f/hid/base.py
pyu2f/hid/linux.py
pyu2f/hid/macos.py
pyu2f/hid/try.py
pyu2f/hid/windows.py